ekata_gateway_processor_helper/__init__.py
ekata_gateway_processor_helper/constants.py
ekata_gateway_processor_helper/exceptions.py
ekata_gateway_processor_helper-0.1.9.dist-info/WHEEL
ekata_gateway_processor_helper-0.1.9.dist-info/METADATA
ekata_gateway_processor_helper-0.1.9.dist-info/RECORD
