Metadata-Version: 2.1
Name: ekata-gateway-processor-helper
Version: 0.1.9
Summary: Backend helper functions for ekata gateway processor
Home-page: https://ekata.io
License: MIT
Keywords: crypto,payment,processor,btc,gateway
Author: EkataIO Wizard
Author-email: support@ekata.io
Requires-Python: >=3.6,<4.0
Classifier: License :: OSI Approved :: MIT License
Classifier: Programming Language :: Python :: 3
Classifier: Programming Language :: Python :: 3.6
Classifier: Programming Language :: Python :: 3.7
Classifier: Programming Language :: Python :: 3.8
Classifier: Programming Language :: Python :: 3.9
Requires-Dist: requests (>=2.27.1,<3.0.0)
Project-URL: Repository, https://gitlab.ekata.io/ekata-io-projects/ekata-gateway-processor-helper-python
